odoo/addons/stock_picking_operations_multilang/README.rst
odoo/addons/stock_picking_operations_multilang/__init__.py
odoo/addons/stock_picking_operations_multilang/__manifest__.py
odoo/addons/stock_picking_operations_multilang/hooks.py
odoo/addons/stock_picking_operations_multilang/i18n/it.po
odoo/addons/stock_picking_operations_multilang/i18n/stock_picking_operations_multilang.pot
odoo/addons/stock_picking_operations_multilang/models/__init__.py
odoo/addons/stock_picking_operations_multilang/models/stock_picking.py
odoo/addons/stock_picking_operations_multilang/models/stock_warehouse.py
odoo/addons/stock_picking_operations_multilang/readme/CONFIGURE.md
odoo/addons/stock_picking_operations_multilang/readme/CONTEXT.md
odoo/addons/stock_picking_operations_multilang/readme/CONTRIBUTORS.md
odoo/addons/stock_picking_operations_multilang/readme/DESCRIPTION.md
odoo/addons/stock_picking_operations_multilang/reports/picking_operations_report.xml
odoo/addons/stock_picking_operations_multilang/reports/report_picking_with_language.xml
odoo/addons/stock_picking_operations_multilang/static/description/icon.png
odoo/addons/stock_picking_operations_multilang/static/description/index.html
odoo/addons/stock_picking_operations_multilang/tests/__init__.py
odoo/addons/stock_picking_operations_multilang/tests/test_stock_picking_operations_multilang.py
odoo/addons/stock_picking_operations_multilang/views/stock_warehouse_views.xml
odoo_addon_stock_picking_operations_multilang-17.0.1.0.0.2.dist-info/METADATA
odoo_addon_stock_picking_operations_multilang-17.0.1.0.0.2.dist-info/WHEEL
odoo_addon_stock_picking_operations_multilang-17.0.1.0.0.2.dist-info/top_level.txt
odoo_addon_stock_picking_operations_multilang-17.0.1.0.0.2.dist-info/RECORD
