Metadata-Version: 2.1
Name: odoo-addon-stock_picking_operations_multilang
Version: 17.0.1.0.0.2
Requires-Python: >=3.10
Requires-Dist: odoo>=17.0a,<17.1dev
Summary: Stock Picking Operations Multilang
Home-page: https://github.com/OCA/stock-logistics-reporting
License: AGPL-3
Author: Quartile, Odoo Community Association (OCA)
Author-email: support@odoo-community.org
Classifier: Programming Language :: Python
Classifier: Framework :: Odoo
Classifier: Framework :: Odoo :: 17.0
Classifier: License :: OSI Approved :: GNU Affero General Public License v3
